djangocms_ads/__init__.py
djangocms_ads/apps.py
djangocms_ads/cms_plugins.py
djangocms_ads/models.py
djangocms_ads/py.typed
djangocms_ads/migrations/0001_initial.py
djangocms_ads/migrations/__init__.py
djangocms_ads/templates/djangocms_ads/default/ad_slot.html
djangocms_ads/templates/djangocms_ads/default/advert.html
djangocms_ads/templates/djangocms_ads/default/container_advanced.html
djangocms_ads/templates/djangocms_ads/default/container_simple.html
djangocms_ads-1.1.2.dist-info/LICENSE
djangocms_ads-1.1.2.dist-info/METADATA
djangocms_ads-1.1.2.dist-info/WHEEL
djangocms_ads-1.1.2.dist-info/top_level.txt
djangocms_ads-1.1.2.dist-info/RECORD
